recently/__init__.py
recently/core.py
recently/duration.py
recently-0.1.2.dist-info/WHEEL
recently-0.1.2.dist-info/entry_points.txt
recently-0.1.2.dist-info/METADATA
recently-0.1.2.dist-info/RECORD
